README.txt
setup.cfg
setup.py
django_linked_items/__info__.py
django_linked_items/__init__.py
django_linked_items/admin.py
django_linked_items/settings.py
django_linked_items/signals.py
django_linked_items/urls.py
django_linked_items.egg-info/PKG-INFO
django_linked_items.egg-info/SOURCES.txt
django_linked_items.egg-info/dependency_links.txt
django_linked_items.egg-info/requires.txt
django_linked_items.egg-info/top_level.txt
django_linked_items/management/__init__.py
django_linked_items/management/commands/__init__.py
django_linked_items/migrations/0001_initial.py
django_linked_items/migrations/__init__.py
django_linked_items/models/__init__.py
django_linked_items/tests/__init__.py
django_linked_items/tests/test_main.py
django_linked_items/tools/__init__.py
django_linked_items/tools/models.py
django_linked_items/tools/relations.py
django_linked_items/views/__init__.py
interface/__init__.py
interface/settings.py
interface/urls.py
interface/wsgi.py