Metadata-Version: 1.1
Name: django-linked-items
Version: 1.0.0.4
Summary: Linked Items
Home-page: https://bitbucket.org/hellwig/django-linked-items/
Author: Martin P. Hellwig
Author-email: martin.hellwig@gmail.com
License: BSD
Download-URL: https://bitbucket.org/hellwig/django-linked-items/get/355fcf3e65a8fa3ef8d6587a4497abcfbcc1291a.zip
Keywords: django,django-integrator
Platform: UNKNOWN
Classifier: Programming Language :: Python :: 3
